humesql/__init__.py
humesql/ai.py
humesql/cli.py
humesql/client.py
humesql/db.py
humesql/utils.py
humesql-0.3.2.dist-info/licenses/LICENSE
humesql-0.3.2.dist-info/METADATA
humesql-0.3.2.dist-info/WHEEL
humesql-0.3.2.dist-info/entry_points.txt
humesql-0.3.2.dist-info/top_level.txt
humesql-0.3.2.dist-info/RECORD
