Metadata-Version: 2.4
Name: humesql
Version: 0.3.2
Summary: Natural language to SQL to JSON results using Gemini.
Home-page: https://github.com/nirajang20/HumeSQL
Author: Nirajan Ghimire
Author-email: nirajanghimire20@gmail.com
Project-URL: Source, https://github.com/nirajang20/HumeSQL
Classifier: Programming Language :: Python :: 3
Classifier: Programming Language :: Python :: 3 :: Only
Classifier: License :: OSI Approved :: MIT License
Classifier: Intended Audience :: Developers
Classifier: Topic :: Database
Classifier: Topic :: Software Development :: Libraries
Requires-Python: >=3.9
License-File: LICENSE
Requires-Dist: mysql-connector-python>=8.0.0
Requires-Dist: google-genai>=0.3.1
Dynamic: author
Dynamic: author-email
Dynamic: classifier
Dynamic: description
Dynamic: description-content-type
Dynamic: home-page
Dynamic: license-file
Dynamic: project-url
Dynamic: requires-dist
Dynamic: requires-python
Dynamic: summary
